diffant/__init__.py
diffant/diffabc.py
diffant/diffini.py
diffant/diffjson.py
diffant/diffxml.py
diffant/diffyml.py
diffant/exceptions.py
diffant/main.py
diffant/nested.py
diffant-1.0.3.dist-info/LICENSE
diffant-1.0.3.dist-info/METADATA
diffant-1.0.3.dist-info/WHEEL
diffant-1.0.3.dist-info/entry_points.txt
diffant-1.0.3.dist-info/RECORD
