Metadata-Version: 2.1
Name: diffant
Version: 1.0.3
Summary: tool to compare structured files like json, ini , yaml
Home-page: https://github.com/omacneil/diffant
License: GPL-3.0-or-later
Keywords: json,yaml,ini,diff,configuration,compare
Author: omacneil
Author-email: dan@omacneil.org
Requires-Python: >=3.8.1,<4.0.0
Classifier: License :: OSI Approved :: GNU General Public License v3 or later (GPLv3+)
Classifier: Programming Language :: Python :: 3
Classifier: Programming Language :: Python :: 3.9
Classifier: Programming Language :: Python :: 3.10
Classifier: Programming Language :: Python :: 3.11
Classifier: Programming Language :: Python :: 3.12
Classifier: Programming Language :: Python :: 3.8
Requires-Dist: pyyaml (==6.0)
Requires-Dist: types-pyyaml (==6.0.12.10)
Requires-Dist: types-xmltodict (==0.13.0.2)
Requires-Dist: xmltodict (==0.13.0)
Project-URL: Repository, https://github.com/omacneil/diffant
